Metadata-Version: 2.1
Name: testware
Version: 1
Summary: Malicious Python Module Experimentation
Home-page: https://github.com/pastewow/testware
Author: dylan
Author-email: d@doop.fun
License: MIT
Project-URL: GitHub, https://github.com/pastewow/testware
Keywords: malware
Classifier: Programming Language :: Python :: 3
Classifier: License :: OSI Approved :: MIT License
Classifier: Operating System :: Microsoft :: Windows
Classifier: Development Status :: 5 - Production/Stable
Classifier: Intended Audience :: Developers
Classifier: Natural Language :: English
Classifier: Topic :: Software Development
